<?xml version="1.0" encoding="UTF-8"?>
<conversation id="CHT_ENG_20130522.0001" medium="CHT" donated="false">
  <messages>
    <message id="m0000" participant="130602" time="2013-05-22 21:32:33 UTC">
      <body>Hey, what's up</body>
    </message>
    <message id="m0001" participant="130529" time="2013-05-22 21:43:36 UTC">
      <body>not much, how are you doing?</body>
    </message>
    <message id="m0002" participant="130602" time="2013-05-22 21:43:54 UTC">
      <body>Ha! Pretty good.</body>
    </message>
    <message id="m0003" participant="130602" time="2013-05-22 21:44:44 UTC">
      <body>Bought a flash drive. 8 gigs for like $7.</body>
    </message>
    <message id="m0004" participant="130602" time="2013-05-22 21:45:04 UTC">
      <body>A few years ago an 8 gig flash drive would have been mindblowing, now it's nothing</body>
    </message>
    <message id="m0005" participant="130529" time="2013-05-22 21:47:36 UTC">
      <body>nice, that's super cheap</body>
    </message>
    <message id="m0006" participant="130529" time="2013-05-22 21:48:02 UTC">
      <body>I've been thinking about getting a new thumb drive</body>
    </message>
    <message id="m0007" participant="130529" time="2013-05-22 21:48:27 UTC">
      <body>I've got a few portable external drives, but having a nice small one would be pretty convenient.</body>
    </message>
    <message id="m0008" participant="130602" time="2013-05-22 21:53:24 UTC">
      <body>Did you see the coverage for the Xbox One?</body>
    </message>
    <message id="m0009" participant="130602" time="2013-05-22 21:54:11 UTC">
      <body>I'm not big into gaming but I'm always interested to see the new systems</body>
    </message>
    <message id="m0010" participant="130529" time="2013-05-22 22:28:58 UTC">
      <body>I haven't. Unfortunately I don't pay attention to either the news or new systems coming out.</body>
    </message>
    <message id="m0011" participant="130529" time="2013-05-22 22:29:13 UTC">
      <body>The last game I actually played was NHL 97 for Genesis</body>
    </message>
    <message id="m0012" participant="130529" time="2013-05-22 22:29:32 UTC">
      <body>What's the skinny on the new Xbox?</body>
    </message>
    <message id="m0013" participant="130602" time="2013-05-22 23:01:17 UTC">
      <body>I just saw some people upset about the games being married to the system</body>
    </message>
    <message id="m0014" participant="130602" time="2013-05-22 23:01:29 UTC">
      <body>so once you install a game on a machine, you can't play that game on any other xbox...</body>
    </message>
    <message id="m0015" participant="130529" time="2013-05-22 23:02:38 UTC">
      <body>ah, weak</body>
    </message>
    <message id="m0016" participant="130529" time="2013-05-22 23:02:59 UTC">
      <body>In general I'm against the trend towards restrictions of that sort</body>
    </message>
    <message id="m0017" participant="130529" time="2013-05-22 23:03:22 UTC">
      <body>mostly I encounter it with music</body>
    </message>
    <message id="m0018" participant="130602" time="2013-05-22 23:05:01 UTC">
      <body>I was thinking about it a few weeks ago - I haven't bought a cd in forever</body>
    </message>
    <message id="m0019" participant="130602" time="2013-05-22 23:05:09 UTC">
      <body>it's so odd</body>
    </message>
    <message id="m0020" participant="130529" time="2013-05-22 23:25:50 UTC">
      <body>Yeah, neither have I</body>
    </message>
    <message id="m0021" participant="130529" time="2013-05-22 23:26:16 UTC">
      <body>it's also gotten to the point where I feel like actually paying money for music has become almost a political thing</body>
    </message>
    <message id="m0022" participant="130529" time="2013-05-22 23:26:38 UTC">
      <body>like I have friends who will get free music, but pay for music from a band who's lesser known</body>
    </message>
    <message id="m0023" participant="130602" time="2013-05-22 23:26:54 UTC">
      <body>yep</body>
    </message>
    <message id="m0024" participant="130602" time="2013-05-22 23:26:56 UTC">
      <body>i do the same</body>
    </message>
    <message id="m0025" participant="130602" time="2013-05-22 23:27:34 UTC">
      <body>If it's some unknown artist and I'm listening to a song or two nonstop and they have an easy purchase option (bandcamp), I'll buy it</body>
    </message>
    <message id="m0026" participant="130529" time="2013-05-22 23:28:25 UTC">
      <body>yeah, but if it's Metallica...</body>
    </message>
    <message id="m0027" participant="130529" time="2013-05-22 23:28:28 UTC">
      <body>jl</body>
    </message>
    <message id="m0028" participant="130529" time="2013-05-22 23:28:31 UTC">
      <body>jk, rather</body>
    </message>
    <message id="m0029" participant="130602" time="2013-05-22 23:28:46 UTC">
      <body>I forgot about all that crazy</body>
    </message>
    <message id="m0030" participant="130529" time="2013-05-22 23:29:17 UTC">
      <body>yeah, I'm not a fan of the band, but I am a HUGE fan of the documentary about them, Some Kind of Monster</body>
    </message>
    <message id="m0031" participant="130529" time="2013-05-22 23:29:20 UTC">
      <body>so good</body>
    </message>
    <message id="m0032" participant="130602" time="2013-05-22 23:30:56 UTC">
      <body>yeah, how have I forgotten to see that</body>
    </message>
    <message id="m0033" participant="130529" time="2013-05-22 23:32:16 UTC">
      <body>I actually had a really difficult time trying to find it on DVD.</body>
    </message>
    <message id="m0034" participant="130529" time="2013-05-22 23:32:43 UTC">
      <body>Searched Blockbuster, Borders, Barnes and Noble and finally found it at some point used at FYE</body>
    </message>
    <message id="m0035" participant="130529" time="2013-05-22 23:32:58 UTC">
      <body>but it's become one of my faves over the years</body>
    </message>
    <message id="m0036" participant="130602" time="2013-05-22 23:34:16 UTC">
      <body>Blockbuster, egads</body>
    </message>
    <message id="m0037" participant="130602" time="2013-05-22 23:34:40 UTC">
      <body>scary how blockbuster and borders are gone</body>
    </message>
    <message id="m0038" participant="130602" time="2013-05-22 23:34:46 UTC">
      <body>wonder how long b&amp;n will last</body>
    </message>
    <message id="m0039" participant="130529" time="2013-05-22 23:35:08 UTC">
      <body>there are still a few blockbusters out there</body>
    </message>
    <message id="m0040" participant="130602" time="2013-05-22 23:35:12 UTC">
      <body>Remember tower records?</body>
    </message>
    <message id="m0041" participant="130602" time="2013-05-22 23:35:21 UTC">
      <body>Yeah, i've seen that - I just can't believe it though.</body>
    </message>
    <message id="m0042" participant="130602" time="2013-05-22 23:35:46 UTC">
      <body>I always figured if I tried to go see a still-existing blockbuster, it would be like trying to find a ghost town. A mirage.</body>
    </message>
    <message id="m0043" participant="130602" time="2013-05-22 23:36:27 UTC">
      <body>You get to where it's supposed to be, and there is just an old white-mustached prospector with a gravelly voice askin how you heard about "The Block Buster"</body>
    </message>
    <message id="m0044" participant="130529" time="2013-05-22 23:37:02 UTC">
      <body>I visit family in South Carolina for the holidays and they've still got one</body>
    </message>
    <message id="m0045" participant="130529" time="2013-05-22 23:37:18 UTC">
      <body>we almost always go there cuz there's nothing else to do</body>
    </message>
    <message id="m0046" participant="130529" time="2013-05-22 23:37:37 UTC">
      <body>but it seems like in most major city areas they're dead dead dead</body>
    </message>
    <message id="m0047" participant="130602" time="2013-05-22 23:39:58 UTC">
      <body>Where are you currently</body>
    </message>
    <message id="m0048" participant="130529" time="2013-05-22 23:43:47 UTC">
      <body>the Philly area</body>
    </message>
    <message id="m0049" participant="130529" time="2013-05-22 23:43:51 UTC">
      <body>how bout you?</body>
    </message>
    <message id="m0050" participant="130602" time="2013-05-22 23:50:18 UTC">
      <body>same</body>
    </message>
    <message id="m0051" participant="130529" time="2013-05-22 23:50:37 UTC">
      <body>nice, how long have you been living here?</body>
    </message>
    <message id="m0052" participant="130602" time="2013-05-22 23:50:53 UTC">
      <body>just a few years</body>
    </message>
    <message id="m0053" participant="130602" time="2013-05-22 23:51:00 UTC">
      <body>you?</body>
    </message>
    <message id="m0054" participant="130529" time="2013-05-22 23:51:37 UTC">
      <body>I'm just about to hit my ten-year mark</body>
    </message>
    <message id="m0055" participant="130529" time="2013-05-22 23:51:50 UTC">
      <body>how do you find it?</body>
    </message>
    <message id="m0056" participant="130602" time="2013-05-22 23:53:54 UTC">
      <body>I was in florida before this, and it is definitely a big change.</body>
    </message>
    <message id="m0057" participant="130602" time="2013-05-22 23:54:13 UTC">
      <body>there is a lot of history here, so that makes up for the appearance of places</body>
    </message>
    <message id="m0058" participant="130602" time="2013-05-22 23:54:18 UTC">
      <body>but it's the reverse there</body>
    </message>
    <message id="m0059" participant="130529" time="2013-05-22 23:55:06 UTC">
      <body>yeah, everything was developed probably in like the 50s-70s there? does that seem about right? or earlier?</body>
    </message>
    <message id="m0060" participant="130602" time="2013-05-22 23:59:39 UTC">
      <body>probably, yeah. It just seems like a city of gold, of streaming light and magic.</body>
    </message>
    <message id="m0061" participant="130602" time="2013-05-23 00:00:04 UTC">
      <body>And so by contrast, philly is like finding an old shack in the woods that Ben Franklin once used</body>
    </message>
    <message id="m0062" participant="130529" time="2013-05-23 00:00:34 UTC">
      <body>humble but functional</body>
    </message>
    <message id="m0063" participant="130529" time="2013-05-23 00:00:46 UTC">
      <body>yeah, I'm a big fan of Philly</body>
    </message>
    <message id="m0064" participant="130529" time="2013-05-23 00:01:17 UTC">
      <body>it's got a great creative pulse, it's cheap, but it's also really urban</body>
    </message>
    <message id="m0065" participant="130529" time="2013-05-23 00:01:38 UTC">
      <body>not in a run-down way so much, though, like Detroit or St. Louis</body>
    </message>
    <message id="m0066" participant="130602" time="2013-05-23 00:02:32 UTC">
      <body>Oh god yeah - Detroit seems like a pre-postapocalyptic wasteland, and St. Louis just seems like a garbage dump that people are forced to live in.</body>
    </message>
    <message id="m0067" participant="130602" time="2013-05-23 00:02:49 UTC">
      <body>Keep in mind I've never been to either place and I'm sure the people there are just lovely, but...</body>
    </message>
    <message id="m0068" participant="130529" time="2013-05-23 00:03:45 UTC">
      <body>no, that's pretty accurate; I've been to both places a few times in the last few years</body>
    </message>
    <message id="m0069" participant="130529" time="2013-05-23 00:12:14 UTC">
      <body>although I did hear that Detroit is starting to hit a new revitalization, now that I come to think about it</body>
    </message>
    <message id="m0070" participant="130529" time="2013-05-23 00:13:21 UTC">
      <body>I think that younger people, artists, hipsters and the like, are starting to forge a path of gentrification that's increasing the population</body>
    </message>
  </messages>
</conversation>
