<?xml version="1.0" encoding="UTF-8"?>
<conversation id="SMS_ENG_20121114.0033" medium="SMS" donated="true">
  <messages>
    <message id="m0000" participant="136729" time="2012-11-14 00:30:40 UTC">
      <body>supdood, u goin to jacobs thing at asb?</body>
    </message>
    <message id="m0001" participant="131015" time="2012-11-14 00:33:32 UTC">
      <body>I haven't heard about it. </body>
    </message>
    <message id="m0002" participant="136729" time="2012-11-14 00:35:39 UTC">
      <body>breese told me they were gonna hit it up round 10. me and my girl were gonna roll thru, might need a place to crash again tho</body>
    </message>
    <message id="m0003" participant="131015" time="2012-11-14 00:48:37 UTC">
      <body>I'll probably try to stop through. Regardless, you guys are welcome to crash at the crib.</body>
    </message>
    <message id="m0004" participant="136729" time="2012-11-14 00:54:06 UTC">
      <body>word, yea, im trying to detox from drinkin, been hittin it too hard. ill txt u in a bit tho</body>
    </message>
    <message id="m0005" participant="131015" time="2012-11-14 00:54:50 UTC">
      <body>Coolio.</body>
    </message>
    <message id="m0006" participant="136729" time="2012-11-14 02:32:49 UTC">
      <body>u at yo crib? might roll up in a bit</body>
    </message>
    <message id="m0007" participant="131015" time="2012-11-14 02:33:31 UTC">
      <body>Headed to ASB in a min.</body>
    </message>
    <message id="m0008" participant="136729" time="2012-11-14 02:36:29 UTC">
      <body>word, holla when u leave there</body>
    </message>
    <message id="m0009" participant="136729" time="2012-11-14 03:44:02 UTC">
      <body>still at asb dawg?</body>
    </message>
    <message id="m0010" participant="131015" time="2012-11-14 03:44:37 UTC">
      <body>Yes sir.</body>
    </message>
    <message id="m0011" participant="136729" time="2012-11-14 03:45:39 UTC">
      <body>word. just got back to the hood. dunno if im drinkin tho</body>
    </message>
    <message id="m0012" participant="131015" time="2012-11-14 03:52:49 UTC">
      <body>Word well I'm here for a.lil if you wanna really see if yr drinking or not.  stop in...</body>
    </message>
    <message id="m0013" participant="136729" time="2012-11-14 03:56:04 UTC">
      <body>haha, shmokey shmokin at my homies</body>
    </message>
    <message id="m0014" participant="131015" time="2012-11-14 04:01:13 UTC">
      <body>Cool cool. Kev just left. I'll hit yalls up when I do too.</body>
    </message>
    <message id="m0015" participant="136729" time="2012-11-14 04:01:50 UTC">
      <body>wordup</body>
    </message>
    <message id="m0016" participant="131015" time="2012-11-14 05:05:07 UTC">
      <body>On my bike. Headed home now.</body>
    </message>
    <message id="m0017" participant="136729" time="2012-11-14 05:17:41 UTC">
      <body>wordup, we're headin that way</body>
    </message>
    <message id="m0018" participant="131015" time="2012-11-14 05:19:14 UTC">
      <body>Ok.</body>
    </message>
  </messages>
</conversation>
