<?xml version="1.0" encoding="UTF-8"?>
<conversation id="SMS_ENG_20121211.0013" medium="SMS" donated="true">
  <messages>
    <message id="m0000" participant="130622" time="2012-12-11 17:50:30 UTC">
      <body>Wait Provincetown? </body>
    </message>
    <message id="m0001" participant="130622" time="2012-12-11 17:50:37 UTC">
      <body>Oh like an hour</body>
    </message>
    <message id="m0002" participant="135350" time="2012-12-11 17:50:56 UTC">
      <body>I'm going to go to jills show in pvd on sat-how far is pvd from booooston?!! </body>
    </message>
    <message id="m0003" participant="135350" time="2012-12-11 17:50:56 UTC">
      <body>Maybe i can come to you after?! I promise not to disturb your studying </body>
    </message>
    <message id="m0004" participant="135350" time="2012-12-11 17:50:56 UTC">
      <body>/writing/making </body>
    </message>
    <message id="m0005" participant="135350" time="2012-12-11 17:50:56 UTC">
      <body>Brown </body>
    </message>
    <message id="m0006" participant="135350" time="2012-12-11 17:50:56 UTC">
      <body>Kk I'm totes coming </body>
    </message>
    <message id="m0007" participant="130622" time="2012-12-11 17:50:58 UTC">
      <body>Oh shit for some reason I thought it was at Micah</body>
    </message>
    <message id="m0008" participant="130622" time="2012-12-11 17:51:02 UTC">
      <body>Oh shit</body>
    </message>
    <message id="m0009" participant="130622" time="2012-12-11 17:51:15 UTC">
      <body>Dude</body>
    </message>
    <message id="m0010" participant="130622" time="2012-12-11 17:51:17 UTC">
      <body>I will cry </body>
    </message>
    <message id="m0011" participant="130622" time="2012-12-11 17:51:53 UTC">
      <body>I'm so miserable I have so much work that I just don't know how to do. And I just miss Hannibal and I am fat. </body>
    </message>
    <message id="m0012" participant="130622" time="2012-12-11 17:52:01 UTC">
      <body>Seeing you would be amazing</body>
    </message>
    <message id="m0013" participant="135350" time="2012-12-11 17:55:12 UTC">
      <body>Yayayayayay! I have Tons of work too so don't worry I will not bug you/just do my work next to you </body>
    </message>
    <message id="m0014" participant="135350" time="2012-12-11 17:55:12 UTC">
      <body>Occasionally we can do quick
coffee breaks :)</body>
    </message>
    <message id="m0015" participant="135350" time="2012-12-11 17:55:12 UTC">
      <body>Call me after 7?</body>
    </message>
    <message id="m0016" participant="135350" time="2012-12-11 17:55:12 UTC">
      <body>However long you want me to? I'm on Xmas break</body>
    </message>
    <message id="m0017" participant="130622" time="2012-12-11 17:55:40 UTC">
      <body>You can work with me??! Wait can I call u</body>
    </message>
    <message id="m0018" participant="130622" time="2012-12-11 17:55:45 UTC">
      <body>Omg this is amazing</body>
    </message>
    <message id="m0019" participant="130622" time="2012-12-11 17:56:00 UTC">
      <body>How long will u stay</body>
    </message>
    <message id="m0020" participant="130622" time="2012-12-11 17:56:02 UTC">
      <body>Ok</body>
    </message>
    <message id="m0021" participant="135350" time="2012-12-11 17:57:20 UTC">
      <body>Friday is my last day </body>
    </message>
    <message id="m0022" participant="135350" time="2012-12-11 17:57:20 UTC">
      <body>When's your last day?! </body>
    </message>
    <message id="m0023" participant="130622" time="2012-12-11 17:59:56 UTC">
      <body>18th</body>
    </message>
    <message id="m0024" participant="130622" time="2012-12-11 18:00:09 UTC">
      <body>Then two papers to write</body>
    </message>
    <message id="m0025" participant="130622" time="2012-12-11 18:00:17 UTC">
      <body>Oh shit</body>
    </message>
    <message id="m0026" participant="130622" time="2012-12-11 18:00:31 UTC">
      <body>You done early</body>
    </message>
    <message id="m0027" participant="130622" time="2012-12-11 18:00:39 UTC">
      <body>Wait are u driving</body>
    </message>
    <message id="m0028" participant="130622" time="2012-12-11 18:00:43 UTC">
      <body>? </body>
    </message>
    <message id="m0029" participant="130622" time="2012-12-11 18:01:01 UTC">
      <body>Let me know bc if so we need to figure out parking</body>
    </message>
    <message id="m0030" participant="130622" time="2012-12-11 18:01:04 UTC">
      <body>It's difficult</body>
    </message>
    <message id="m0031" participant="130622" time="2012-12-11 18:01:15 UTC">
      <body>I wouldn't drive if u can avoid it</body>
    </message>
    <message id="m0032" participant="130622" time="2012-12-11 18:01:29 UTC">
      <body>We can discuss after seven</body>
    </message>
    <message id="m0033" participant="135350" time="2012-12-11 18:05:52 UTC">
      <body>No not driving </body>
    </message>
    <message id="m0034" participant="135350" time="2012-12-11 18:05:52 UTC">
      <body>Def not driving hahaha </body>
    </message>
  </messages>
</conversation>
