<?xml version="1.0" encoding="UTF-8"?>
<conversation id="SMS_ENG_20130925.0009" medium="SMS" donated="true">
  <messages>
    <message id="m0000" time="2013-09-25 20:36:01 UTC" participant="152417">
      <body>Richards kitchen os 13/hr. and this is the view from the 863togo office ￼</body>
    </message>
    <message id="m0001" time="2013-09-25 20:37:50 UTC" participant="152560">
      <body>Hey that's a great starting wage! And what a lovely view of the Onion!</body>
    </message>
    <message id="m0002" time="2013-09-25 21:24:24 UTC" participant="152560">
      <body>Ahhhhhhhhh my apartment stinks like cigarettes :(</body>
    </message>
    <message id="m0003" time="2013-09-25 21:27:39 UTC" participant="152417">
      <body>Stop smoking then :-p</body>
    </message>
    <message id="m0004" time="2013-09-25 21:29:10 UTC" participant="152560">
      <body>Hey now. How am I ever going to sound like Tom Waits or Leonard Cohen?</body>
    </message>
  </messages>
</conversation>

