<?xml version="1.0" encoding="UTF-8"?>
<conversation id="SMS_ENG_20150203.0009" medium="SMS" donated="true">
  <messages>
    <message id="m0000" time="2015-02-03 14:35:30 UTC" participant="152212">
      <body>￼Finally did this. </body>
    </message>
    <message id="m0001" time="2015-02-03 14:40:40 UTC" participant="152311">
      <body>Oh that is just too too good!!! I am in my cAfe writing and got this and oh you are so f- ing good. Your ability to combine ideas with visuals w humor w spontaneity... Damn!</body>
    </message>
  </messages>
</conversation>

