<?xml version="1.0" encoding="UTF-8"?>
<conversation id="SMS_ENG_20131020.0005" medium="SMS" donated="true">
  <messages>
    <message id="m0000" time="2013-10-20 17:07:04 UTC" participant="153631">
      <body>Movie plan?</body>
    </message>
    <message id="m0001" time="2013-10-20 17:42:07 UTC" participant="153548">
      <body>Hey! We ride bikes down here!</body>
    </message>
    <message id="m0002" time="2013-10-20 17:42:30 UTC" participant="153548">
      <body>Got here early to hang, will save you guys seats.</body>
    </message>
    <message id="m0003" time="2013-10-20 17:46:40 UTC" participant="153631">
      <body>Ok see you soon!</body>
    </message>
    <message id="m0004" time="2013-10-20 18:05:22 UTC" participant="153548">
      <body>The line is so long!</body>
    </message>
    <message id="m0005" time="2013-10-20 18:16:19 UTC" participant="153631">
      <body>It's cool I just drove a million miles in the wrong direction</body>
    </message>
    <message id="m0006" time="2013-10-20 18:23:16 UTC" participant="153548">
      <body>One of my students Mona is taking tickets she's fromaustin.</body>
    </message>
    <message id="m0007" time="2013-10-20 18:25:04 UTC" participant="153631">
      <body>We're in the line now. Probably y'all won't get to save seats but thanks for trying :(</body>
    </message>
    <message id="m0008" time="2013-10-20 18:25:04 UTC" participant="153631">
      <body>Actually we're moving pretty quick</body>
    </message>
    <message id="m0009" time="2013-10-20 18:26:24 UTC" participant="153631">
      <body>I remain hopeful</body>
    </message>
    <message id="m0010" time="2013-10-20 18:27:30 UTC" participant="153548">
      <body>I think we can hold off these old people</body>
    </message>
    <message id="m0011" time="2013-10-20 18:31:26 UTC" participant="153631">
      <body>Oh now I see her</body>
    </message>
  </messages>
</conversation>

