<?xml version="1.0" encoding="UTF-8"?>
<conversation id="SMS_ENG_20121111.0014" medium="SMS" donated="true">
  <messages>
    <message id="m0000" participant="130730" time="2012-11-11 16:31:12 UTC">
      <body>Hey, happy birthday.</body>
    </message>
    <message id="m0001" participant="130664" time="2012-11-11 17:04:52 UTC">
      <body>Hey, thanks!</body>
    </message>
    <message id="m0002" participant="130664" time="2012-11-30 01:53:36 UTC">
      <body>Do you have a power point night for auction week this year?</body>
    </message>
    <message id="m0003" participant="130730" time="2012-11-30 02:03:06 UTC">
      <body> grad schools at the same time. This one is called "self helping for broken humans"</body>
    </message>
    <message id="m0004" participant="130730" time="2012-11-30 02:03:07 UTC">
      <body>Yes! Its on monday the 10th. I have some little flyers with the wrong date in west phl. I am running kind of a shitshow this year because im applying to</body>
    </message>
    <message id="m0005" participant="130664" time="2012-11-30 02:13:18 UTC">
      <body>Oh awesome, I will come out. Where are you applying to grad school? I was surprised to see Kay's work on display at my school! There's a couch wheat paste too</body>
    </message>
    <message id="m0006" participant="130730" time="2012-11-30 15:52:05 UTC">
      <body>￼Check out this picture of israel and palestine that one of my clients did. Zero input from staff, i just found it on a pile of papers. Might be too small to read unless you have one of those smartphones.</body>
    </message>
    <message id="m0007" participant="130664" time="2012-11-30 16:09:26 UTC">
      <body>Fortunately my phone is super smart. Do you know who made it? Looks like HAARP is at it again...</body>
    </message>
    <message id="m0008" participant="130730" time="2012-11-30 16:15:02 UTC">
      <body>Its this autistic girl named andrea. Shes from romania</body>
    </message>
    <message id="m0009" participant="130664" time="2012-11-30 17:03:55 UTC">
      <body>What kind of other stuff does she make? </body>
    </message>
    <message id="m0010" participant="130730" time="2012-11-30 17:05:09 UTC">
      <body>Pictures of her doll collection. And national tragedies like 911 and jfk.</body>
    </message>
    <message id="m0011" participant="130730" time="2012-11-30 17:05:47 UTC">
      <body>But mostly dolls. Like real wackadoodle looking dolls.</body>
    </message>
    <message id="m0012" participant="130664" time="2012-11-30 17:08:14 UTC">
      <body>Wow..wow. </body>
    </message>
    <message id="m0013" participant="130664" time="2012-12-01 21:30:28 UTC">
      <body>We came out of retrograde on Tuesday, my mistake. We are in post retrograde until dec 14..things are slowly getting better</body>
    </message>
    <message id="m0014" participant="130730" time="2012-12-02 02:03:00 UTC">
      <body>Science robots from nasa found ice on mercury, i read it in the paper today.</body>
    </message>
    <message id="m0015" participant="130664" time="2012-12-02 02:31:48 UTC">
      <body>Yeah I read about , organic matter too. Ice on the planet closest to the sun..</body>
    </message>
    <message id="m0016" participant="130730" time="2012-12-02 02:32:36 UTC">
      <body>That means aliens</body>
    </message>
    <message id="m0017" participant="130664" time="2012-12-02 02:34:44 UTC">
      <body>My Egyptian archaeology professor finally said the word aliens this week, I've been waiting all semester</body>
    </message>
    <message id="m0020" participant="130730" time="2012-12-02 02:41:05 UTC">
      <body>What are you going to learn about ancient astronauts?</body>
    </message>
    <message id="m0021" participant="130664" time="2012-12-02 02:44:03 UTC">
      <body>So many secrets. The paper I'm writing now is about gobekli tepe</body>
    </message>
    <message id="m0022" participant="130730" time="2012-12-02 19:45:48 UTC">
      <body>What is gobleki tepe?</body>
    </message>
    <message id="m0023" participant="130664" time="2012-12-02 21:01:45 UTC">
      <body>It's a ritual site from the tenth century BCE with sophisticated wall carvings and giant monoliths. It's from a time when people were hunter gatherers and previously considered primitive. </body>
    </message>
    <message id="m0024" participant="130664" time="2012-12-02 21:02:15 UTC">
      <body>The people that used it covered it with twenty feet of sand when they left.</body>
    </message>
    <message id="m0025" participant="130730" time="2012-12-10 17:02:55 UTC">
      <body>Tonite at space 1026, self help pwrpnt comedy, 8pm show, 730 doors, 1026 arch st. FREE</body>
    </message>
    <message id="m0026" participant="130664" time="2012-12-10 18:46:40 UTC">
      <body>Would it be uncouth to fill my pockets with beer?</body>
    </message>
    <message id="m0027" participant="130730" time="2012-12-10 19:17:52 UTC">
      <body>Its encouraged.</body>
    </message>
    <message id="m0028" participant="130664" time="2012-12-11 00:07:00 UTC">
      <body>I'm going to practice self help by studying hard tonight, but skool is finished this week, maybe I will see u soon </body>
    </message>
    <message id="m0029" participant="130730" time="2012-12-16 23:56:32 UTC">
      <body>￼</body>
    </message>
    <message id="m0030" participant="130664" time="2012-12-17 00:30:44 UTC">
      <body>Is this a PSA?</body>
    </message>
    <message id="m0031" participant="130730" time="2012-12-17 00:31:31 UTC">
      <body>Nah, just santa claus.</body>
    </message>
    <message id="m0032" participant="130664" time="2012-12-17 00:50:38 UTC">
      <body>Cool I will watch my thrash cans. Will u be at comedy dreamz Tuesday?</body>
    </message>
    <message id="m0033" participant="130730" time="2012-12-17 01:25:25 UTC">
      <body>Yeah, i will. Would you want to hang out beforehand?</body>
    </message>
    <message id="m0034" participant="130664" time="2012-12-17 02:21:32 UTC">
      <body>That'd be cool what were u thinking?</body>
    </message>
    <message id="m0035" participant="130730" time="2012-12-17 02:57:50 UTC">
      <body>Nothing in particular. Just whatevz.</body>
    </message>
    <message id="m0036" participant="130664" time="2012-12-17 03:13:43 UTC">
      <body>I love whatevz..</body>
    </message>
    <message id="m0037" participant="130664" time="2012-12-18 17:39:21 UTC">
      <body>Want to meet for food around seven? Someplace with beer!</body>
    </message>
    <message id="m0038" participant="130730" time="2012-12-18 20:24:33 UTC">
      <body>7ish sounds good. I have no preference.</body>
    </message>
    <message id="m0039" participant="130664" time="2012-12-18 21:24:40 UTC">
      <body>I want to be close to Barbary bc I will be wo bike. 7:30 at Johnny Brenda's?</body>
    </message>
    <message id="m0040" participant="130730" time="2012-12-18 21:54:42 UTC">
      <body>Perfect</body>
    </message>
    <message id="m0041" participant="130730" time="2012-12-19 00:13:28 UTC">
      <body>Hey, are you close? Im getting ready to leave.</body>
    </message>
    <message id="m0042" participant="130664" time="2012-12-19 00:14:20 UTC">
      <body>I'm still waiting for the el may be a little late</body>
    </message>
    <message id="m0043" participant="130730" time="2012-12-19 00:15:01 UTC">
      <body>Ok no problem</body>
    </message>
    <message id="m0044" participant="130664" time="2012-12-19 00:30:51 UTC">
      <body>Ok eastbound</body>
    </message>
    <message id="m0045" participant="130730" time="2012-12-19 00:50:07 UTC">
      <body>All the way in the back</body>
    </message>
    <message id="m0046" participant="130730" time="2012-12-19 16:22:36 UTC">
      <body>￼The play tomorrow is at 8pm at wolf cycles, and there seems to be music too, so no hurry. The play is called Mother Mother Ocean, and it costs 3 dollars.</body>
    </message>
    <message id="m0047" participant="130664" time="2012-12-19 16:27:14 UTC">
      <body>Cool, thanks, I will probably come out. #itwasgoodseeingyou</body>
    </message>
    <message id="m0048" participant="130664" time="2012-12-20 17:43:00 UTC">
      <body>I'm wearing your shirt..even the things that aren't swasticas seem to capture the essence of swasticas</body>
    </message>
    <message id="m0049" participant="130730" time="2013-01-04 14:48:18 UTC">
      <body>Yo. does you gots a twitter?</body>
    </message>
    <message id="m0050" participant="130664" time="2013-01-04 15:23:13 UTC">
      <body>Sorta, I only made it to subscribe to Ella's</body>
    </message>
    <message id="m0051" participant="130730" time="2013-01-04 15:29:50 UTC">
      <body>Woah, she tweets?</body>
    </message>
    <message id="m0052" participant="130664" time="2013-01-04 16:42:59 UTC">
      <body>Like a lot. Why do you ask if I have one?</body>
    </message>
    <message id="m0053" participant="130730" time="2013-01-04 16:51:40 UTC">
      <body>I got one and im trying to understand it</body>
    </message>
    <message id="m0054" participant="130664" time="2013-01-04 16:54:40 UTC">
      <body>Maybe Ella could explain it? </body>
    </message>
    <message id="m0055" participant="130730" time="2013-01-04 16:59:02 UTC">
      <body>Shes probably more tech savvy than both of us.</body>
    </message>
    <message id="m0056" participant="130664" time="2013-01-04 17:59:57 UTC">
      <body>Probably, but she would be a little condescending</body>
    </message>
    <message id="m0057" participant="130730" time="2013-01-09 22:53:52 UTC">
      <body>￼</body>
    </message>
    <message id="m0058" participant="130664" time="2013-01-09 23:42:47 UTC">
      <body>The realest</body>
    </message>
    <message id="m0059" participant="130664" time="2013-01-10 19:50:05 UTC">
      <body>Do you know about Mel's hole?</body>
    </message>
    <message id="m0060" participant="130730" time="2013-01-10 19:54:16 UTC">
      <body>No idea</body>
    </message>
    <message id="m0061" participant="130664" time="2013-01-10 20:08:13 UTC">
      <body>I will send you a link to the coast to coast audio. Listen to all of it, it's so good</body>
    </message>
    <message id="m0062" participant="130730" time="2013-01-10 20:11:44 UTC">
      <body>Hahaha yes! Coast to coast rules</body>
    </message>
    <message id="m0063" participant="130730" time="2013-01-10 20:13:52 UTC">
      <body/>
    </message>
    <message id="m0064" participant="130730" time="2013-01-10 20:13:52 UTC">
      <body>Is that like blue hole in New Jersey?</body>
    </message>
    <message id="m0065" participant="130664" time="2013-01-10 20:14:22 UTC">
      <body>It's a good one. Part of the hollow earth theory. This guy has land with a bottomless hole. Then the gov took it, then he found another</body>
    </message>
    <message id="m0066" participant="130664" time="2013-01-10 20:14:42 UTC">
      <body>One</body>
    </message>
    <message id="m0067" participant="130664" time="2013-01-10 20:16:35 UTC">
      <body>Sorta, but they lowered a sheep into it and then cut a tumor out of it and a highly intelligent seal was born</body>
    </message>
    <message id="m0068" participant="130664" time="2013-01-10 20:17:34 UTC">
      <body>Art bell is losing his shit</body>
    </message>
    <message id="m0069" participant="130730" time="2013-01-10 20:17:43 UTC">
      <body>Ha</body>
    </message>
    <message id="m0070" participant="130664" time="2013-01-17 15:50:26 UTC">
      <body>I'll say it, you'll hear it, you'll do it, I'll get it, you'll learn it, I'll live with it and you'll die without it</body>
    </message>
    <message id="m0071" participant="130730" time="2013-01-18 02:31:28 UTC">
      <body>Hahaha neck tattoos, sheesh!</body>
    </message>
    <message id="m0072" participant="130730" time="2013-01-18 03:19:33 UTC">
      <body>￼</body>
    </message>
    <message id="m0073" participant="130730" time="2013-01-18 14:09:00 UTC">
      <body>Have you ever been to the abandoned pa turnpike? I'm trying to go there this weekend</body>
    </message>
    <message id="m0074" participant="130664" time="2013-01-18 17:48:24 UTC">
      <body>No I never have, my friend went and said he couldn't walk all the way through the tunnel. Too scurred</body>
    </message>
    <message id="m0075" participant="130730" time="2013-01-18 18:12:16 UTC">
      <body>You have to go through the tunnel first?</body>
    </message>
    <message id="m0076" participant="130664" time="2013-01-18 18:21:04 UTC">
      <body>I think the tunnel is optional</body>
    </message>
    <message id="m0077" participant="130664" time="2013-01-20 23:05:48 UTC">
      <body>Did u go to the turnpike?</body>
    </message>
    <message id="m0078" participant="130730" time="2013-01-20 23:07:18 UTC">
      <body>I'm in Pittsburgh now, going to try and find it on the way back tomorrow, totally misjudged how far it was from pgh</body>
    </message>
    <message id="m0079" participant="130664" time="2013-01-20 23:10:28 UTC">
      <body> I thought it was like mid west pa. Good luck!!!</body>
    </message>
    <message id="m0080" participant="130730" time="2013-01-20 23:12:08 UTC">
      <body>It is, closer to the middle. I'll send you pictures</body>
    </message>
    <message id="m0081" participant="130730" time="2013-01-22 04:22:24 UTC">
      <body>￼It was so spooky but I didn't get picked up by any canibals</body>
    </message>
    <message id="m0082" participant="130664" time="2013-01-22 17:34:38 UTC">
      <body>Was there a barking German Shepard with live ammo strapped to its back?</body>
    </message>
    <message id="m0083" participant="130730" time="2013-01-22 18:22:56 UTC">
      <body>￼Just some ads for goth restaurants</body>
    </message>
    <message id="m0084" participant="130730" time="2013-02-25 14:21:52 UTC">
      <body>http://www.youtube.com/watch?v=HtaSWZM2mMU&amp;sns=em</body>
    </message>
    <message id="m0085" participant="130730" time="2013-02-25 14:22:20 UTC">
      <body/>
    </message>
    <message id="m0086" participant="130664" time="2013-02-25 19:31:39 UTC">
      <body>Pillz and wine</body>
    </message>
    <message id="m0087" participant="130730" time="2013-02-25 19:38:51 UTC">
      <body>Everything about that video blows my mind, especially the weird video art and nazi van at the end</body>
    </message>
    <message id="m0088" participant="130664" time="2013-02-25 21:00:10 UTC">
      <body>Yeah it's all magical. The geographic panels of static are nice</body>
    </message>
    <message id="m0089" participant="130664" time="2013-02-25 21:10:54 UTC">
      <body>No phone, I meant geometric </body>
    </message>
    <message id="m0090" participant="130664" time="2013-03-08 23:26:23 UTC">
      <body>Hey is the pddc show tonight? </body>
    </message>
    <message id="m0091" participant="130730" time="2013-03-09 00:14:28 UTC">
      <body>Yeah, until 9</body>
    </message>
    <message id="m0092" participant="130664" time="2013-03-09 05:26:04 UTC">
      <body>Sorry I missed it, I'm on spring break next week if u want to ride bikes or drink beers</body>
    </message>
    <message id="m0093" participant="130730" time="2013-03-09 06:13:20 UTC">
      <body>It's my spring break too, got the week off</body>
    </message>
    <message id="m0094" participant="130664" time="2013-03-09 06:15:49 UTC">
      <body>What! Do you have something going on?</body>
    </message>
    <message id="m0095" participant="130730" time="2013-03-09 06:19:44 UTC">
      <body>Taking a week off, interview at Pratt and whateverz</body>
    </message>
    <message id="m0096" participant="130664" time="2013-03-09 06:35:31 UTC">
      <body>Cool good luck with ur interview</body>
    </message>
    <message id="m0097" participant="130730" time="2013-03-09 06:36:48 UTC">
      <body>Thanx! </body>
    </message>
    <message id="m0098" participant="130664" time="2013-03-09 06:38:59 UTC">
      <body>Is that the portfolio u decided on?</body>
    </message>
    <message id="m0099" participant="130730" time="2013-03-09 06:49:36 UTC">
      <body>Yup! And this￼</body>
    </message>
    <message id="m0100" participant="130664" time="2013-03-09 19:02:55 UTC">
      <body>Lets drive to the ocean or something. MTV spring break</body>
    </message>
    <message id="m0101" participant="130730" time="2013-03-09 21:58:45 UTC">
      <body>Yeah! I would like that. I'm going to be in NYC for a few days starting tomorrow, but later in the week would be good</body>
    </message>
    <message id="m0102" participant="130664" time="2013-03-09 22:03:51 UTC">
      <body>Cool let me know when u r back. Don't forget your mandarin wedges </body>
    </message>
    <message id="m0103" participant="130664" time="2013-04-18 20:57:09 UTC">
      <body>Hey! I have a friend at Bryn Mawr who wants to do art therapy, and she's looking for an internship, anything at all, do you think there is anything she could do at pddc? </body>
    </message>
    <message id="m0104" participant="130730" time="2013-04-19 02:37:52 UTC">
      <body>Yeah, she should email Linda Price at lprice@arcpddc.org and mention you and me.</body>
    </message>
    <message id="m0105" participant="130664" time="2013-04-19 03:12:23 UTC">
      <body>Awesome, her name is Lija, and she's a good egg. Thanks!</body>
    </message>
    <message id="m0106" participant="130730" time="2013-04-19 03:14:08 UTC">
      <body>How have you been?</body>
    </message>
    <message id="m0107" participant="130664" time="2013-04-19 03:17:33 UTC">
      <body>Good, my brains all melty, but school is done in two weeks. Got accepted for this year long curating thing at school, found out today good newz</body>
    </message>
    <message id="m0108" participant="130730" time="2013-04-19 03:20:10 UTC">
      <body>What's the curating thing?</body>
    </message>
    <message id="m0109" participant="130664" time="2013-04-19 03:22:24 UTC">
      <body>It's like an intensive program with the head of special collections, curating a show of their art collection for credit. I get to do it instead of a class next yr</body>
    </message>
    <message id="m0110" participant="130730" time="2013-04-19 03:22:40 UTC">
      <body>That's great! Is that an assistantship?</body>
    </message>
    <message id="m0111" participant="130664" time="2013-04-19 03:31:03 UTC">
      <body>No, it's a type of class Bryn Mawr offers, it's meant to give field experience. It's pretty selective, had an annoying application process. What's new w u?</body>
    </message>
    <message id="m0112" participant="130730" time="2013-04-19 03:34:28 UTC">
      <body>I've been super busy, just finished 2 zines put out by other people who want to "publish" my stuff. Also got into Pratt and preparing for that.</body>
    </message>
    <message id="m0113" participant="130664" time="2013-04-19 03:36:22 UTC">
      <body>Awesome! Congrats. When do you move? </body>
    </message>
    <message id="m0114" participant="130730" time="2013-04-19 03:39:12 UTC">
      <body>Orientation is August 23, so some time around then. NYC is intimidatingly expensive and that's my biggest concern. They offered me some scholarship money and an assistantship, so that's a small cushion</body>
    </message>
    <message id="m0115" participant="130730" time="2013-04-19 03:43:08 UTC">
      <body>I've been feeling more goth than ever before, but also more positive than ever, basically </body>
    </message>
    <message id="m0116" participant="130664" time="2013-04-19 03:44:46 UTC">
      <body>Maybe there is a correlation? I've been pretty posi too, maybe the haarp frequency changed?</body>
    </message>
    <message id="m0117" participant="130730" time="2013-04-19 03:45:46 UTC">
      <body>I think that could be it</body>
    </message>
    <message id="m0118" participant="130664" time="2013-04-19 03:49:01 UTC">
      <body>spring break 4ever</body>
    </message>
    <message id="m0119" participant="130730" time="2013-04-19 03:54:40 UTC">
      <body>http://youtu.be/r5-fXh-VP5g</body>
    </message>
    <message id="m0120" participant="130664" time="2013-04-19 04:01:49 UTC">
      <body>I need serious extensions</body>
    </message>
    <message id="m0121" participant="130730" time="2013-04-19 04:02:30 UTC">
      <body>Me too!</body>
    </message>
    <message id="m0122" participant="130664" time="2013-04-19 04:02:57 UTC">
      <body>Yes! </body>
    </message>
  </messages>
</conversation>
