<?xml version="1.0" encoding="UTF-8"?>
<conversation id="SMS_ENG_20130127.0017" medium="SMS" donated="true">
  <messages>
    <message id="m0000" participant="135386" time="2013-01-27 16:25:36 UTC">
      <body>How's your weekend. I'm gonna be bummed to leave DC tomro </body>
    </message>
    <message id="m0001" participant="130622" time="2013-01-27 16:27:07 UTC">
      <body>Ahhhhh you having a good time?</body>
    </message>
    <message id="m0002" participant="135386" time="2013-01-27 16:27:39 UTC">
      <body>Yes! Not freaked out by kids</body>
    </message>
    <message id="m0003" participant="135386" time="2013-01-27 16:27:44 UTC">
      <body>little girl is now my new BFF. She's 4. She was piggy backing in the kitchen last nite</body>
    </message>
    <message id="m0004" participant="135386" time="2013-01-27 16:27:44 UTC">
      <body>My aunt and cousin left me alone all day with her. She's cool</body>
    </message>
    <message id="m0005" participant="130622" time="2013-01-27 16:27:45 UTC">
      <body>Hahaaa</body>
    </message>
    <message id="m0006" participant="130622" time="2013-01-27 16:27:50 UTC">
      <body>What happened</body>
    </message>
    <message id="m0007" participant="130622" time="2013-01-27 16:28:39 UTC">
      <body>Kids are awesome </body>
    </message>
    <message id="m0008" participant="135386" time="2013-01-27 16:29:52 UTC">
      <body>Really?</body>
    </message>
    <message id="m0009" participant="130622" time="2013-01-27 16:30:55 UTC">
      <body>Yeah kids are awesome.  I want one</body>
    </message>
    <message id="m0010" participant="130622" time="2013-01-27 16:31:18 UTC">
      <body>Yeah.  I totally want kids</body>
    </message>
    <message id="m0011" participant="135386" time="2013-01-27 16:49:04 UTC">
      <body>I don't really</body>
    </message>
    <message id="m0012" participant="135386" time="2013-01-27 16:49:04 UTC">
      <body>I enjoy company of kids now but I'd prob suck at having one</body>
    </message>
  </messages>
</conversation>
