<?xml version="1.0" encoding="UTF-8"?>
<conversation id="SMS_ENG_20141004.0011" medium="SMS" donated="true">
  <messages>
    <message id="m0000" time="2014-10-04 01:36:44 UTC" participant="153547">
      <body>Hey, do you wanna come to my place and check out some art this weekend. I am packing stuff up for me show next week</body>
    </message>
    <message id="m0001" time="2014-10-04 01:38:08 UTC" participant="153598">
      <body>I'm in NJ for the weekend. I'll come by after you get the pieces back. No rush.</body>
    </message>
  </messages>
</conversation>

