<?xml version="1.0" encoding="UTF-8"?>
<conversation id="SMS_ENG_20140903.0000" medium="SMS" donated="true">
  <messages>
    <message id="m0000" time="2014-09-03 00:02:54 UTC" participant="149306">
      <body>I'm sort of cash low, you wana meet up at pasqualies for a bit. Also I need to get up early so sooner than later would be better for me</body>
    </message>
    <message id="m0001" time="2014-09-03 00:05:54 UTC" participant="149368">
      <body>Sure. I kinda want a cocktail at fiume. I'll buy you one, too. Meet at 9?</body>
    </message>
    <message id="m0002" time="2014-09-03 00:06:44 UTC" participant="149306">
      <body>Ok at Fiume if it's not packed</body>
    </message>
    <message id="m0003" time="2014-09-03 00:07:09 UTC" participant="149368">
      <body>Cool.</body>
    </message>
  </messages>
</conversation>

